flask_supercache/__init__.py
flask_supercache/backends.py
flask_supercache/query_cache.py
flask_supercache-1.0.0.dist-info/licenses/LICENSE
flask_supercache-1.0.0.dist-info/METADATA
flask_supercache-1.0.0.dist-info/WHEEL
flask_supercache-1.0.0.dist-info/top_level.txt
flask_supercache-1.0.0.dist-info/RECORD
