Metadata-Version: 2.4
Name: flask-supercache
Version: 1.0.0
Summary: A 3-tier caching system for Flask with zero external dependencies
Home-page: https://github.com/wallmarkets/flask-supercache
Author: wallmarkets Team
Author-email: team@wallmarkets.store
Project-URL: Bug Reports, https://github.com/wallmarkets/flask-supercache/issues
Project-URL: Source, https://github.com/wallmarkets/flask-supercache
Project-URL: Documentation, https://github.com/wallmarkets/flask-supercache#readme
Keywords: flask cache caching redis lru ttl performance
Classifier: Development Status :: 5 - Production/Stable
Classifier: Intended Audience :: Developers
Classifier: License :: OSI Approved :: MIT License
Classifier: Operating System :: OS Independent
Classifier: Programming Language :: Python :: 3
Classifier: Programming Language :: Python :: 3.7
Classifier: Programming Language :: Python :: 3.8
Classifier: Programming Language :: Python :: 3.9
Classifier: Programming Language :: Python :: 3.10
Classifier: Programming Language :: Python :: 3.11
Classifier: Framework :: Flask
Classifier: Topic :: Software Development :: Libraries :: Python Modules
Classifier: Topic :: Internet :: WWW/HTTP :: Dynamic Content
Requires-Python: >=3.7
License-File: LICENSE
Requires-Dist: Flask>=2.0.0
Requires-Dist: flask-caching>=1.10.0
Provides-Extra: redis
Requires-Dist: redis>=3.5.0; extra == "redis"
Provides-Extra: dev
Requires-Dist: pytest>=7.0.0; extra == "dev"
Requires-Dist: pytest-cov>=3.0.0; extra == "dev"
Requires-Dist: black>=22.0.0; extra == "dev"
Requires-Dist: flake8>=4.0.0; extra == "dev"
Requires-Dist: mypy>=0.950; extra == "dev"
Dynamic: author
Dynamic: author-email
Dynamic: classifier
Dynamic: description
Dynamic: description-content-type
Dynamic: home-page
Dynamic: keywords
Dynamic: license-file
Dynamic: project-url
Dynamic: provides-extra
Dynamic: requires-dist
Dynamic: requires-python
Dynamic: summary
